{
"meta":{"test_sets":[],"test_metrics":[],"learn_metrics":[{"best_value":"Min","name":"RMSE"}],"launch_mode":"Train","parameters":"","iteration_count":100,"learn_sets":["learn"],"name":"experiment"},
"iterations":[
{"learn":[14.005006],"iteration":0,"passed_time":0.000520941081,"remaining_time":0.05157316702},
{"learn":[13.14441192],"iteration":1,"passed_time":0.0009205796503,"remaining_time":0.04510840286},
{"learn":[12.34258257],"iteration":2,"passed_time":0.00178042985,"remaining_time":0.05756723181},
{"learn":[11.64527793],"iteration":3,"passed_time":0.002393807456,"remaining_time":0.05745137894},
{"learn":[11.02766183],"iteration":4,"passed_time":0.003537111718,"remaining_time":0.06720512264},
{"learn":[10.43485794],"iteration":5,"passed_time":0.004561892822,"remaining_time":0.07146965422},
{"learn":[9.890641275],"iteration":6,"passed_time":0.005520385424,"remaining_time":0.07334226349},
{"learn":[9.492161212],"iteration":7,"passed_time":0.006385430451,"remaining_time":0.07343245019},
{"learn":[9.105082953],"iteration":8,"passed_time":0.007324624988,"remaining_time":0.0740600971},
{"learn":[8.674157135],"iteration":9,"passed_time":0.007970244344,"remaining_time":0.0717321991},
{"learn":[8.341743544],"iteration":10,"passed_time":0.008646650954,"remaining_time":0.06995926681},
{"learn":[8.049372916],"iteration":11,"passed_time":0.009338912987,"remaining_time":0.06848536191},
{"learn":[7.757318612],"iteration":12,"passed_time":0.01073266099,"remaining_time":0.07182626968},
{"learn":[7.522206899],"iteration":13,"passed_time":0.0119712192,"remaining_time":0.07353748935},
{"learn":[7.297756655],"iteration":14,"passed_time":0.01283521099,"remaining_time":0.07273286228},
{"learn":[7.088359431],"iteration":15,"passed_time":0.01430034526,"remaining_time":0.07507681263},
{"learn":[6.882113791],"iteration":16,"passed_time":0.01493608872,"remaining_time":0.07292325669},
{"learn":[6.704728832],"iteration":17,"passed_time":0.01588915465,"remaining_time":0.07238392674},
{"learn":[6.563881962],"iteration":18,"passed_time":0.0170484625,"remaining_time":0.07268028748},
{"learn":[6.418790279],"iteration":19,"passed_time":0.01790913168,"remaining_time":0.07163652674},
{"learn":[6.315756953],"iteration":20,"passed_time":0.01871571903,"remaining_time":0.07040675256},
{"learn":[6.210157751],"iteration":21,"passed_time":0.01951844533,"remaining_time":0.06920176072},
{"learn":[6.115058449],"iteration":22,"passed_time":0.02016583677,"remaining_time":0.06751171439},
{"learn":[6.014819884],"iteration":23,"passed_time":0.02137750341,"remaining_time":0.06769542748},
{"learn":[5.93117229],"iteration":24,"passed_time":0.02226969208,"remaining_time":0.06680907624},
{"learn":[5.844857622],"iteration":25,"passed_time":0.02294628183,"remaining_time":0.06530864829},
{"learn":[5.771145213],"iteration":26,"passed_time":0.02355948453,"remaining_time":0.06369786557},
{"learn":[5.704018229],"iteration":27,"passed_time":0.02426731184,"remaining_time":0.06240165901},
{"learn":[5.665806474],"iteration":28,"passed_time":0.02486799955,"remaining_time":0.06088372304},
{"learn":[5.616500369],"iteration":29,"passed_time":0.02543049205,"remaining_time":0.05933781479},
{"learn":[5.558023666],"iteration":30,"passed_time":0.02628415901,"remaining_time":0.0585034507},
{"learn":[5.510080976],"iteration":31,"passed_time":0.02702266349,"remaining_time":0.05742315991},
{"learn":[5.468747792],"iteration":32,"passed_time":0.02785573084,"remaining_time":0.05655557474},
{"learn":[5.429275534],"iteration":33,"passed_time":0.02842753611,"remaining_time":0.05518286421},
{"learn":[5.402117324],"iteration":34,"passed_time":0.02919615049,"remaining_time":0.05422142233},
{"learn":[5.367635151],"iteration":35,"passed_time":0.02965106097,"remaining_time":0.05271299728},
{"learn":[5.345181232],"iteration":36,"passed_time":0.03034664458,"remaining_time":0.05167131374},
{"learn":[5.319151269],"iteration":37,"passed_time":0.03104423382,"remaining_time":0.05065111834},
{"learn":[5.296134146],"iteration":38,"passed_time":0.03195275326,"remaining_time":0.0499773833},
{"learn":[5.269629003],"iteration":39,"passed_time":0.03282144361,"remaining_time":0.04923216542},
{"learn":[5.251147059],"iteration":40,"passed_time":0.03351761849,"remaining_time":0.04823267051},
{"learn":[5.248003302],"iteration":41,"passed_time":0.03386719129,"remaining_time":0.04676897844},
{"learn":[5.232376509],"iteration":42,"passed_time":0.03453712348,"remaining_time":0.04578176834},
{"learn":[5.213524255],"iteration":43,"passed_time":0.03532070022,"remaining_time":0.04495361846},
{"learn":[5.189691584],"iteration":44,"passed_time":0.03612686984,"remaining_time":0.04415506314},
{"learn":[5.166052198],"iteration":45,"passed_time":0.03663555281,"remaining_time":0.0430069533},
{"learn":[5.140406659],"iteration":46,"passed_time":0.03743486939,"remaining_time":0.04221378889},
{"learn":[5.118929684],"iteration":47,"passed_time":0.03826203131,"remaining_time":0.04145053391},
{"learn":[5.108792602],"iteration":48,"passed_time":0.03902788211,"remaining_time":0.04062085689},
{"learn":[5.098141225],"iteration":49,"passed_time":0.03969142494,"remaining_time":0.03969142494},
{"learn":[5.085926393],"iteration":50,"passed_time":0.04049811346,"remaining_time":0.03890995215},
{"learn":[5.067816804],"iteration":51,"passed_time":0.04125675729,"remaining_time":0.03808316057},
{"learn":[5.049834901],"iteration":52,"passed_time":0.04200507764,"remaining_time":0.03724978583},
{"learn":[5.03838627],"iteration":53,"passed_time":0.04307869089,"remaining_time":0.03669666261},
{"learn":[5.033534248],"iteration":54,"passed_time":0.0435420996,"remaining_time":0.03562535422},
{"learn":[5.023726885],"iteration":55,"passed_time":0.0443722319,"remaining_time":0.03486389649},
{"learn":[5.01290392],"iteration":56,"passed_time":0.04489460964,"remaining_time":0.03386786341},
{"learn":[5.005569127],"iteration":57,"passed_time":0.04565282167,"remaining_time":0.03305893983},
{"learn":[4.989969032],"iteration":58,"passed_time":0.04618829949,"remaining_time":0.03209695389},
{"learn":[4.976762446],"iteration":59,"passed_time":0.04689349595,"remaining_time":0.03126233064},
{"learn":[4.967222715],"iteration":60,"passed_time":0.04774924537,"remaining_time":0.03052820606},
{"learn":[4.954407599],"iteration":61,"passed_time":0.04845417123,"remaining_time":0.02969771785},
{"learn":[4.942125056],"iteration":62,"passed_time":0.04915290665,"remaining_time":0.0288675801},
{"learn":[4.930230716],"iteration":63,"passed_time":0.04992807467,"remaining_time":0.028084542},
{"learn":[4.921695642],"iteration":64,"passed_time":0.05054804913,"remaining_time":0.0272181803},
{"learn":[4.906405625],"iteration":65,"passed_time":0.05105684665,"remaining_time":0.02630201191},
{"learn":[4.894330248],"iteration":66,"passed_time":0.05159547045,"remaining_time":0.0254126944},
{"learn":[4.88211557],"iteration":67,"passed_time":0.05211383247,"remaining_time":0.02452415646},
{"learn":[4.877946398],"iteration":68,"passed_time":0.0526278718,"remaining_time":0.02364440617},
{"learn":[4.863182126],"iteration":69,"passed_time":0.05343877292,"remaining_time":0.02290233125},
{"learn":[4.84646533],"iteration":70,"passed_time":0.05418402549,"remaining_time":0.02213150337},
{"learn":[4.838014752],"iteration":71,"passed_time":0.05489255175,"remaining_time":0.02134710346},
{"learn":[4.82981137],"iteration":72,"passed_time":0.05554907898,"remaining_time":0.02054554976},
{"learn":[4.817094767],"iteration":73,"passed_time":0.05676116679,"remaining_time":0.01994311265},
{"learn":[4.808314151],"iteration":74,"passed_time":0.0574786848,"remaining_time":0.0191595616},
{"learn":[4.796235023],"iteration":75,"passed_time":0.05806741278,"remaining_time":0.01833707772},
{"learn":[4.784434534],"iteration":76,"passed_time":0.05885175192,"remaining_time":0.01757909473},
{"learn":[4.774402487],"iteration":77,"passed_time":0.05942325434,"remaining_time":0.01676040507},
{"learn":[4.76731896],"iteration":78,"passed_time":0.06003013113,"remaining_time":0.01595737663},
{"learn":[4.75934113],"iteration":79,"passed_time":0.0607847527,"remaining_time":0.01519618818},
{"learn":[4.754106378],"iteration":80,"passed_time":0.06143394949,"remaining_time":0.0144104326},
{"learn":[4.744002932],"iteration":81,"passed_time":0.06216967392,"remaining_time":0.01364700159},
{"learn":[4.731700554],"iteration":82,"passed_time":0.06278473512,"remaining_time":0.01285952406},
{"learn":[4.723284153],"iteration":83,"passed_time":0.0635604289,"remaining_time":0.01210674836},
{"learn":[4.712232782],"iteration":84,"passed_time":0.06432280036,"remaining_time":0.01135108242},
{"learn":[4.703046867],"iteration":85,"passed_time":0.06505502317,"remaining_time":0.01059035261},
{"learn":[4.698601855],"iteration":86,"passed_time":0.06569622484,"remaining_time":0.009816677275},
{"learn":[4.692429407],"iteration":87,"passed_time":0.06634581809,"remaining_time":0.009047157012},
{"learn":[4.675027364],"iteration":88,"passed_time":0.06704754755,"remaining_time":0.00828677554},
{"learn":[4.662368584],"iteration":89,"passed_time":0.06750017152,"remaining_time":0.007500019058},
{"learn":[4.646206172],"iteration":90,"passed_time":0.06814238424,"remaining_time":0.006739356684},
{"learn":[4.641245848],"iteration":91,"passed_time":0.06872209098,"remaining_time":0.005975833999},
{"learn":[4.633900435],"iteration":92,"passed_time":0.06931959122,"remaining_time":0.00521760364},
{"learn":[4.624738236],"iteration":93,"passed_time":0.07001474475,"remaining_time":0.004469026261},
{"learn":[4.612798287],"iteration":94,"passed_time":0.07060184367,"remaining_time":0.003715886509},
{"learn":[4.605222001],"iteration":95,"passed_time":0.07126559502,"remaining_time":0.002969399793},
{"learn":[4.601725912],"iteration":96,"passed_time":0.07177053218,"remaining_time":0.002219707181},
{"learn":[4.59722371],"iteration":97,"passed_time":0.07216523863,"remaining_time":0.001472759972},
{"learn":[4.580235665],"iteration":98,"passed_time":0.07309593665,"remaining_time":0.0007383427945},
{"learn":[4.57591791],"iteration":99,"passed_time":0.07394722072,"remaining_time":0}
]}